obscure64-0.1.0.dist-info/METADATA
obscure64-0.1.0.dist-info/WHEEL
obscure64-0.1.0.dist-info/licenses/LICENSE
obscure64/__init__.py
obscure64-0.1.0.dist-info/RECORD
